README.rst
setup.py
dbarray/__init__.py
django_dbarray.egg-info/PKG-INFO
django_dbarray.egg-info/SOURCES.txt
django_dbarray.egg-info/dependency_links.txt
django_dbarray.egg-info/top_level.txt