Metadata-Version: 1.1
Name: django-dbarray
Version: 0.0.1
Summary: Django ORM field for Postgres array types.
Home-page: http://github.com/ecometrica/django-vinaigrette/
Author: Michael Mulley
Author-email: michael@michaelmulley.com
License: UNKNOWN
Keywords: django,model,field,postgres,postgresql,database,array,list
Platform: UNKNOWN
Classifier: Programming Language :: Python
Classifier: Programming Language :: Python :: 2.6
Classifier: Development Status :: 3 - Alpha
Classifier: License :: OSI Approved :: BSD License
Classifier: Operating System :: POSIX
Classifier: Topic :: Database
Classifier: Framework :: Django
